{
    "version": "https://jsonfeed.org/version/1",
    "title": "欢迎 • All posts by \"document\" category",
    "description": "正在建设中...",
    "home_page_url": "https://ningchenhui.github.io",
    "items": [
        {
            "id": "https://ningchenhui.github.io/Document/Seminar/pdf220421/",
            "url": "https://ningchenhui.github.io/Document/Seminar/pdf220421/",
            "title": "SIREx Part 1",
            "date_published": "2022-04-20T16:00:00.000Z",
            "content_html": "<p>[文献阅读汇报] 海冰动力学 SIREx Part 1<span id=\"more\"></span></p>\n\n\n\t<div class=\"row\">\n    <embed src=\"2022.04.21-海冰.pdf\" width=\"100%\" height=\"550\" type=\"application/pdf\">\n\t</div>\n\n\n",
            "tags": [
                "pdf"
            ]
        },
        {
            "id": "https://ningchenhui.github.io/Document/Seminar/pdf220331/",
            "url": "https://ningchenhui.github.io/Document/Seminar/pdf220331/",
            "title": "Arctic Sea Ice Deformation",
            "date_published": "2022-03-30T16:00:00.000Z",
            "content_html": "<p>[文献阅读汇报] 海冰动力学<span id=\"more\"></span></p>\n<p><object data=\"2022.03.31-海冰.pdf\" width=\"100%\" height=\"500px\"></object></p>\n",
            "tags": [
                "pdf"
            ]
        },
        {
            "id": "https://ningchenhui.github.io/Document/seufile/",
            "url": "https://ningchenhui.github.io/Document/seufile/",
            "title": "课程资料分享",
            "date_published": "2020-09-26T12:04:31.000Z",
            "content_html": "<p>Course Documents Sharing   <span id=\"more\"></span></p>\n<p>最近开始整理学过的课程的资料，包括课件、笔记等等。<br>\n提取码无说明则为 tzsg</p>\n<h2 id=\"数学\"><a class=\"markdownIt-Anchor\" href=\"#数学\">#</a> 数学</h2>\n<h3 id=\"数学分析\"><a class=\"markdownIt-Anchor\" href=\"#数学分析\">#</a> 数学分析</h3>\n<p><strong>习题课课件：</strong><span class=\"exturl\" data-url=\"aHR0cHM6Ly9wYW4uYmFpZHUuY29tL3MvMU9xRk81X0RzbV9ETHN3cnB4c0cwMXc=\">PDF 与 PowerPoint</span><br>\n<strong> 大一数分课件：</strong><span class=\"exturl\" data-url=\"aHR0cHM6Ly9wYW4uYmFpZHUuY29tL3MvMVRiRnJ1dTdmUTE2OFBJQnpHMEtKRmc=\">PDF 与 PowerPoint</span><br>\n<strong> 数分 3 作业解答：</strong><span class=\"exturl\" data-url=\"aHR0cHM6Ly9wYW4uYmFpZHUuY29tL3MvMThjWklMbFNnSkctLThUejk0aEJYQkE=\">老师答案照片</span><br>\n<strong>数分 3 笔记：</strong><span class=\"exturl\" data-url=\"aHR0cHM6Ly9wYW4uYmFpZHUuY29tL3MvMW1HZ3VZbmVzTUIxV0MtUnBRaTdoY0E=\">复习笔记照片</span> 自己整理的<br>\n<strong>参考书：</strong><br>\n- <span class=\"exturl\" data-url=\"aHR0cHM6Ly9wYW4uYmFpZHUuY29tL3MvMVZYTW4xYU1XeW92cFYxUTZ2MExCeEE=\">数学分析中的典型问题和方法 (第 2 版)- 裴礼文 - 扫描版.pdf</span><br>\n- <span class=\"exturl\" data-url=\"aHR0cHM6Ly9wYW4uYmFpZHUuY29tL3MvMXE1cERjX2pTY2thYUxhUkFTWW9fbGc=\">吉米多维奇 共 3 册</span></p>\n<h3 id=\"复变函数\"><a class=\"markdownIt-Anchor\" href=\"#复变函数\">#</a> 复变函数</h3>\n<p><strong>使用的英文教材：</strong><span class=\"exturl\" data-url=\"aHR0cHM6Ly9wYW4uYmFpZHUuY29tL3MvMTFnbzNzUHNVUEVNMG9keFZKbHhFMkE=\">复分析 (Elias M. Stein, Rami Shakarchi).pdf</span> 提取码: jjte<br>\n<strong> 中文参考书：</strong><span class=\"exturl\" data-url=\"aHR0cHM6Ly9wYW4uYmFpZHUuY29tL3MvMXc3ckpWVTkzdldlM3VXV2drYkhzclE=\">复变函数论.pdf</span> 提取码: d8m3</p>\n<h3 id=\"实变函数\"><a class=\"markdownIt-Anchor\" href=\"#实变函数\">#</a> 实变函数</h3>\n<p><strong>参考书：</strong><span class=\"exturl\" data-url=\"aHR0cHM6Ly9wYW4uYmFpZHUuY29tL3MvMTBHb2dhOTNNbEs2alZEV01STHY0Wmc=\">《实变函数论 第二版》周民强 北京大学 2008 年 5 月第 2 版</span><br>\n<strong>习题解答：</strong><span class=\"exturl\" data-url=\"aHR0cHM6Ly9wYW4uYmFpZHUuY29tL3MvMW9zQ1NOd09RRUI1cmg3TnFGenM0dEE=\">实变函数习题答案.pdf</span></p>\n<h3 id=\"金融模型及计算\"><a class=\"markdownIt-Anchor\" href=\"#金融模型及计算\">#</a> 金融模型及计算</h3>\n<p><strong>知识点整理：</strong><span class=\"exturl\" data-url=\"aHR0cHM6Ly9wYW4uYmFpZHUuY29tL3MvMXp3YzdLUjlIcnlUUnZlZFR0MG8tbWc=\">期权定价.pdf</span> 提取码: 5auu 嗯也是我自己整理的。</p>\n<h3 id=\"最优化方法\"><a class=\"markdownIt-Anchor\" href=\"#最优化方法\">#</a> 最优化方法</h3>\n<p><strong>课件：</strong><span class=\"exturl\" data-url=\"aHR0cHM6Ly9wYW4uYmFpZHUuY29tL3MvMXhzb0VmUmR3dnFKMTRyeFdIN2R5d3c=\">PowerPoint</span><br>\n<strong> 课后习题解答：</strong><span class=\"exturl\" data-url=\"aHR0cHM6Ly9wYW4uYmFpZHUuY29tL3MvMVAtWXdhdlo0WEc0SDJSc0pBbmVVdXc=\">最优化理论与算法习题解答.pdf</span></p>\n<h3 id=\"常微分方程\"><a class=\"markdownIt-Anchor\" href=\"#常微分方程\">#</a> 常微分方程</h3>\n<p><strong>课件：</strong><span class=\"exturl\" data-url=\"aHR0cHM6Ly9wYW4uYmFpZHUuY29tL3MvMXZaekRfT293N0dLWnZfd05OSE9GWGc=\">PDF 与 PowerPoint</span><br>\n<strong> 习题解答：</strong><span class=\"exturl\" data-url=\"aHR0cHM6Ly9wYW4uYmFpZHUuY29tL3MvMW5TNENMdDQxM29KVTJMTmtEa0NNdkE=\">常微分方程教程 - 丁同仁 (第二版)- 习题解答.pdf</span><br>\n<strong> 笔记：</strong><span class=\"exturl\" data-url=\"aHR0cHM6Ly9wYW4uYmFpZHUuY29tL3MvMWdKODl0SG8zTUc4dFVyQjRUZW55YkE=\">复习笔记照片</span> 自己整理的</p>\n<h3 id=\"微分方程引论\"><a class=\"markdownIt-Anchor\" href=\"#微分方程引论\">#</a> 微分方程引论</h3>\n<p><strong>教案：</strong><span class=\"exturl\" data-url=\"aHR0cHM6Ly9wYW4uYmFpZHUuY29tL3MvMWs5Mm1SNF9DQlE1OGlPbWJZWk1wVXc=\">数物方程.pdf</span> 这是老师自己写的教案，偷偷用<br>\n<strong>课后习题解答：</strong> 来自网络，实在做不出来再看哦<br>\n - <span class=\"exturl\" data-url=\"aHR0cHM6Ly93d3cuZG9jaW4uY29tL3AtMTIyNjk0NzI3MC5odG1s\">第一章：波动方程</span><br>\n - <span class=\"exturl\" data-url=\"aHR0cHM6Ly9tYXguYm9vazExOC5jb20vaHRtbC8yMDE4LzA0MTYvMTYxNzA5Njc4LnNodG0=\">第二章：热传导方程</span><br>\n - <span class=\"exturl\" data-url=\"aHR0cHM6Ly93ZW5rdS5iYWlkdS5jb20vdmlldy8xYjg1YmYzNzMxMTI2ZWRiNmYxYTEwOTcuaHRtbA==\">第三章：调和方程</span><br>\n - <span class=\"exturl\" data-url=\"aHR0cHM6Ly93d3cuZG9jODguY29tL3AtNTU5NTk5ODI1MjU3MC5odG1s\">第四章：偏微分方程分类总结</span><br>\n<strong>其他参考：</strong><br>\n- <span class=\"exturl\" data-url=\"aHR0cHM6Ly93d3cuZG9jaW4uY29tL3AtMTI4MDU4NzEzNy5odG1sP2RvY2Zyb209cnJlbGE=\">数学物理方程 (谷超豪第二版) 习题全解</span><br>\n - <span class=\"exturl\" data-url=\"aHR0cHM6Ly93ZW5rdS5iYWlkdS5jb20vdmlldy82ZTk1MWJjNTllYzNkNWJiZmQwYTc0OTEuaHRtbA==\">一阶偏微分方程基本知识</span></p>\n<h2 id=\"统计学\"><a class=\"markdownIt-Anchor\" href=\"#统计学\">#</a> 统计学</h2>\n<h3 id=\"概率论\"><a class=\"markdownIt-Anchor\" href=\"#概率论\">#</a> 概率论</h3>\n<p><strong>课件：</strong><span class=\"exturl\" data-url=\"aHR0cHM6Ly9wYW4uYmFpZHUuY29tL3MvMWVqNE5OcEpRM3Rzcl9Femh1bllhMFE=\">概率论课件.pdf</span><br>\n<strong> 作业解答：</strong><span class=\"exturl\" data-url=\"aHR0cHM6Ly9wYW4uYmFpZHUuY29tL3MvMV9EZjVFQ2ZYSWhRaXM2S2FCMjE5S3c=\">HW-0X-Prob.pdf</span> 老师给的答案<br>\n<strong>考点：</strong><span class=\"exturl\" data-url=\"aHR0cHM6Ly9wYW4uYmFpZHUuY29tL3MvMVNTVWpLbFNIcEJkcFRIYzlfZGE1SlE=\">概率论考点.docx</span><br>\n<strong> 笔记：</strong><span class=\"exturl\" data-url=\"aHR0cHM6Ly9wYW4uYmFpZHUuY29tL3MvMXlvV3N6S3VObnhBMVFGNkZlU1g4LUE=\">复习笔记照片</span> 自己整理的<br>\n<strong>参考书：</strong><span class=\"exturl\" data-url=\"aHR0cHM6Ly9wYW4uYmFpZHUuY29tL3MvMXhLbEdmd1pOdFMzQlM4eF9rR0ZKa2c=\">概率论基础 复旦大学 李贤平 第三版.pdf</span></p>\n<h3 id=\"数理统计\"><a class=\"markdownIt-Anchor\" href=\"#数理统计\">#</a> 数理统计</h3>\n<p><strong>课件：</strong><span class=\"exturl\" data-url=\"aHR0cHM6Ly9wYW4uYmFpZHUuY29tL3MvMVdvZkdfRWM3UHZYdGRrbjF2LUwwamc=\">PowerPoint</span><br>\n<strong> 参考书：</strong><span class=\"exturl\" data-url=\"aHR0cHM6Ly9wYW4uYmFpZHUuY29tL3MvMWV6ZEpVb2VNV29LbFc3cU5vNGlwakE=\">概率论与数理统计（陈希孺）.pdf</span></p>\n<h2 id=\"数值计算\"><a class=\"markdownIt-Anchor\" href=\"#数值计算\">#</a> 数值计算</h2>\n<h3 id=\"科学计算前沿\"><a class=\"markdownIt-Anchor\" href=\"#科学计算前沿\">#</a> 科学计算前沿</h3>\n<p><strong>课件：</strong><span class=\"exturl\" data-url=\"aHR0cHM6Ly9wYW4uYmFpZHUuY29tL3MvMUZmNWJCaXRKSkp3cGdKR2xHTHNFdFE=\">PowerPoint 与文献</span><br>\n<strong>课件整合：</strong><span class=\"exturl\" data-url=\"aHR0cHM6Ly9wYW4uYmFpZHUuY29tL3MvMWNLZUxTRXhUbWhkektUMXFJVDVncXc=\">科学计算前沿 v2.rar</span> 自己整理并排版，开卷考试就靠它啦</p>\n<h3 id=\"数值分析\"><a class=\"markdownIt-Anchor\" href=\"#数值分析\">#</a> 数值分析</h3>\n<p><strong>课件：</strong><span class=\"exturl\" data-url=\"aHR0cHM6Ly9wYW4uYmFpZHUuY29tL3MvMWJCeVBlTG0zV1RMN3JxVmdqWFBVOXc=\">PowerPoint 与教学大纲</span></p>\n<h2 id=\"计算机\"><a class=\"markdownIt-Anchor\" href=\"#计算机\">#</a> 计算机</h2>\n<h3 id=\"matlab编程与应用\"><a class=\"markdownIt-Anchor\" href=\"#matlab编程与应用\">#</a> MATLAB 编程与应用</h3>\n<p><strong>教材：</strong><br>\n- <span class=\"exturl\" data-url=\"aHR0cHM6Ly9wYW4uYmFpZHUuY29tL3MvMTNCNlUxRjZnenRFWnQ1b2poWjlNbVE=\">MATLAB 高效编程技巧与应用_25 个案例分析_完整版.pdf</span><br>\n- <span class=\"exturl\" data-url=\"aHR0cHM6Ly9wYW4uYmFpZHUuY29tL3MvMWIwemNQZ05vYzVBRE9ab1I1UFZncVE=\">MATLAB 编程 (第二版).pdf</span><br>\n<strong> 配套资源：</strong><span class=\"exturl\" data-url=\"aHR0cHM6Ly9wYW4uYmFpZHUuY29tL3MvMVZaYl9xRHIyVUNkeHNRcU5pSU5mWVE=\">25Example 程序和数据.zip</span><br>\n<strong> 参考资料：</strong><span class=\"exturl\" data-url=\"aHR0cHM6Ly9wYW4uYmFpZHUuY29tL3MvMWlMdUNUbjg0NjFXYUxGaG9BOTJURXc=\">Matlab 内训课件</span> 是从慕课上找的课件</p>\n<h3 id=\"数据结构\"><a class=\"markdownIt-Anchor\" href=\"#数据结构\">#</a> 数据结构</h3>\n<p><strong>课件：</strong><span class=\"exturl\" data-url=\"aHR0cHM6Ly9wYW4uYmFpZHUuY29tL3MvMU0wN04waG9QNzJwdTVBT2pocjEyRWc=\">PowerPoint 与教学进度表</span></p>\n<h3 id=\"计算机图形学\"><a class=\"markdownIt-Anchor\" href=\"#计算机图形学\">#</a> 计算机图形学</h3>\n<p><strong>课程大作业：</strong><span class=\"exturl\" data-url=\"aHR0cHM6Ly96aGVuZ2JpbGkuZ2l0aHViLmlvL3Byb2dyYW1zL0NvbXB1dGVyR3JhcGhpY3Mv\">Only My Cube</span> 我们自己做的游戏，不可照抄，仅供参考！@oc 大佬 (其实是放上来秀的嘿嘿</p>\n<h2 id=\"英语\"><a class=\"markdownIt-Anchor\" href=\"#英语\">#</a> 英语</h2>\n<p><strong>Llama 测试软件:</strong><span class=\"exturl\" data-url=\"aHR0cHM6Ly9wYW4uYmFpZHUuY29tL3MvMU5WSExsaGs1ZTl5OUpiek5RZkxRcXc=\">LLAMA</span> 一个用于测试学其他语言难度的软件？<br>\n<strong>雅思:</strong><span class=\"exturl\" data-url=\"aHR0cHM6Ly9wYW4uYmFpZHUuY29tL3MvMS0yU2Q2aXNaRVZRV3MzdUYtR0YyeHc=\"> 剑桥雅思 7，8，9 教材</span></p>\n",
            "tags": [
                "Coarse"
            ]
        }
    ]
}